mcp_lightcast/__init__.py
mcp_lightcast/__main__.py
mcp_lightcast/server.py
mcp_lightcast/apis/__init__.py
mcp_lightcast/apis/base.py
mcp_lightcast/apis/career_pathways.py
mcp_lightcast/apis/classification.py
mcp_lightcast/apis/job_postings.py
mcp_lightcast/apis/occupation_benchmark.py
mcp_lightcast/apis/similarity.py
mcp_lightcast/apis/skills.py
mcp_lightcast/apis/titles.py
mcp_lightcast/auth/__init__.py
mcp_lightcast/auth/oauth.py
mcp_lightcast/tools/__init__.py
mcp_lightcast/tools/classification_tools.py
mcp_lightcast/tools/job_postings_tools.py
mcp_lightcast/tools/normalize_title_get_skills.py
mcp_lightcast/tools/occupation_benchmark_tools.py
mcp_lightcast/tools/similarity_tools.py
mcp_lightcast/tools/skills_tools.py
mcp_lightcast/tools/titles_tools.py
mcp_lightcast/tools/unified_skills.py
mcp_lightcast/tools/workflow_tools.py
mcp_lightcast/utils/__init__.py
mcp_lightcast/utils/version_manager.py
mcp_lightcast-0.2.1.dist-info/METADATA
mcp_lightcast-0.2.1.dist-info/WHEEL
mcp_lightcast-0.2.1.dist-info/entry_points.txt
mcp_lightcast-0.2.1.dist-info/licenses/LICENSE
mcp_lightcast-0.2.1.dist-info/RECORD
