Metadata-Version: 2.4
Name: mcp-lightcast
Version: 0.2.1
Summary: MCP server for Lightcast API integration using FastMCP
Project-URL: Homepage, https://github.com/your-username/mcp-lightcast
Project-URL: Repository, https://github.com/your-username/mcp-lightcast
Project-URL: Issues, https://github.com/your-username/mcp-lightcast/issues
Project-URL: Documentation, https://github.com/your-username/mcp-lightcast/blob/main/README.md
Project-URL: Changelog, https://github.com/your-username/mcp-lightcast/releases
Author: Lawrence Wu
Maintainer: Lawrence Wu
License: MIT
License-File: LICENSE
Keywords: api,fastmcp,job-titles,lightcast,mcp,skills
Classifier: Development Status :: 4 - Beta
Classifier: Intended Audience :: Developers
Classifier: License :: OSI Approved :: MIT License
Classifier: Operating System :: OS Independent
Classifier: Programming Language :: Python :: 3
Classifier: Programming Language :: Python :: 3.12
Classifier: Topic :: Internet :: WWW/HTTP :: HTTP Servers
Classifier: Topic :: Scientific/Engineering :: Information Analysis
Classifier: Topic :: Software Development :: Libraries :: Python Modules
Requires-Python: >=3.12
Requires-Dist: click>=8.0.0
Requires-Dist: fastmcp>=2.11.0
Requires-Dist: httpx>=0.25.0
Requires-Dist: pydantic-settings>=2.0.0
Requires-Dist: pydantic>=2.0.0
Requires-Dist: python-dotenv>=1.0.0
